plover_retro_case/__init__.py
plover_retro_case/change_case.py
plover_retro_case/commands.py
plover_retro_case-0.1.2.dist-info/DESCRIPTION.rst
plover_retro_case-0.1.2.dist-info/METADATA
plover_retro_case-0.1.2.dist-info/RECORD
plover_retro_case-0.1.2.dist-info/WHEEL
plover_retro_case-0.1.2.dist-info/entry_points.txt
plover_retro_case-0.1.2.dist-info/metadata.json
plover_retro_case-0.1.2.dist-info/top_level.txt
plover_retro_case-0.1.2.dist-info/zip-safe
