Metadata-Version: 2.0
Name: plover-retro-case
Version: 0.1.2
Summary: Retroactively change the case of an already written word
Home-page: https://github.com/LukeSilva/plover_retro_case
Author: Luke Silva
Author-email: luke@lukesilva.com
License: GNU General Public License v3 or later (GPLv3+)
Keywords: plover plover_plugin
Platform: UNKNOWN
Classifier: Development Status :: 4 - Beta
Classifier: Environment :: Plugins
Classifier: Intended Audience :: End Users/Desktop
Classifier: License :: OSI Approved :: GNU General Public License v3 or later (GPLv3+)
Classifier: Operating System :: OS Independent
Classifier: Programming Language :: Python :: 3
Classifier: Programming Language :: Python :: 3.6
Requires-Dist: plover (>=4.0.0.dev7)
